SimLogger/FigLogger.py
SimLogger/SimLogger.py
SimLogger/SimNotify.py
SimLogger/__init__.py
simlogger-0.4.2.dist-info/METADATA
simlogger-0.4.2.dist-info/WHEEL
simlogger-0.4.2.dist-info/licenses/LICENSE
simlogger-0.4.2.dist-info/RECORD
