Metadata-Version: 2.3
Name: SimLogger
Version: 0.4.2
Summary: Simplify scientific data logging
Author-email: Joey Kilgore <joey.a.kilgore@gmail.com>
License-File: LICENSE
Requires-Dist: figurl
Requires-Dist: gitpython
Requires-Dist: pandas
Requires-Dist: plotly
Provides-Extra: doc
Requires-Dist: sphinx; extra == 'doc'
Requires-Dist: sphinx-rtd-theme; extra == 'doc'
Provides-Extra: lint
Requires-Dist: pre-commit; extra == 'lint'
Provides-Extra: test
Requires-Dist: pytest; extra == 'test'
